sensible_types/__init__.py
sensible_types/positive_int.py
sensible_types/py.typed
sensible_types-0.2.0.dist-info/METADATA
sensible_types-0.2.0.dist-info/WHEEL
sensible_types-0.2.0.dist-info/licenses/LICENSE
sensible_types-0.2.0.dist-info/RECORD
