Metadata-Version: 2.3
Name: sensible-types
Version: 0.2.0
Summary: A collection of useful types for Python, to drive correctness in your programs.
Project-URL: Repository, https://github.com/juancoquet/sensible-types
Author-email: Juan Coquet <69824312+juancoquet@users.noreply.github.com>
Requires-Python: >=3.12
Requires-Dist: pydantic>=2.9.2
